mopidy_muse/__init__.py
mopidy_muse/ext.conf
mopidy_muse/static/404.html
mopidy_muse/static/android-chrome-192x192.png
mopidy_muse/static/android-chrome-512x512.png
mopidy_muse/static/apple-touch-icon-120x120.png
mopidy_muse/static/apple-touch-icon-152x152.png
mopidy_muse/static/apple-touch-icon-60x60.png
mopidy_muse/static/apple-touch-icon-76x76.png
mopidy_muse/static/favicon.ico
mopidy_muse/static/icon.png
mopidy_muse/static/icon.svg
mopidy_muse/static/index.html
mopidy_muse/static/manifest.json
mopidy_muse/static/_app/env.js
mopidy_muse/static/_app/version.json
mopidy_muse/static/_app/immutable/assets/0.DHuOrve7.css
mopidy_muse/static/_app/immutable/assets/10.DHe6zdoB.css
mopidy_muse/static/_app/immutable/assets/4.CGATCLBD.css
mopidy_muse/static/_app/immutable/assets/6.HeIq3WR5.css
mopidy_muse/static/_app/immutable/assets/7.CDMOhFK4.css
mopidy_muse/static/_app/immutable/assets/8.CwshEKiO.css
mopidy_muse/static/_app/immutable/assets/9.BPOo451a.css
mopidy_muse/static/_app/immutable/assets/FontAwesomeIcon.BFiS3c8t.css
mopidy_muse/static/_app/immutable/assets/SnapGroups.CS18Rfxi.css
mopidy_muse/static/_app/immutable/assets/_layout.C5YXFhuO.css
mopidy_muse/static/_app/immutable/assets/_page.1RJkzHKo.css
mopidy_muse/static/_app/immutable/assets/_page.CJmxitXL.css
mopidy_muse/static/_app/immutable/assets/_page.D-9vMo_m.css
mopidy_muse/static/_app/immutable/assets/_page.DHe6zdoB.css
mopidy_muse/static/_app/immutable/assets/_page.DWYf0HJ8.css
mopidy_muse/static/_app/immutable/assets/_page.HeIq3WR5.css
mopidy_muse/static/_app/immutable/assets/mopidyTools.BFiS3c8t.css
mopidy_muse/static/_app/immutable/chunks/SnapGroups.D-CE2XNy.js
mopidy_muse/static/_app/immutable/chunks/await_block.Bclaoo_x.js
mopidy_muse/static/_app/immutable/chunks/clickOutside.BxFJ2b6i.js
mopidy_muse/static/_app/immutable/chunks/entry.Dtmeg57J.js
mopidy_muse/static/_app/immutable/chunks/index.BKUCHbCk.js
mopidy_muse/static/_app/immutable/chunks/index.BpksQ4ni.js
Mopidy_Muse-0.0.36.dist-info/LICENSE
Mopidy_Muse-0.0.36.dist-info/METADATA
Mopidy_Muse-0.0.36.dist-info/WHEEL
Mopidy_Muse-0.0.36.dist-info/entry_points.txt
Mopidy_Muse-0.0.36.dist-info/top_level.txt
Mopidy_Muse-0.0.36.dist-info/RECORD
