Metadata-Version: 2.1
Name: Mopidy-Muse
Version: 0.0.36
Summary: Mopidy interface with snapcast support
Author: Cristian Brokate
License: Apache License
Project-URL: Homepage, https://cristianpb.github.io/blog/mopidy-muse
Project-URL: Documentation, https://github.com/cristianpb/muse
Project-URL: Repository, https://github.com/cristianpb/muse.git
Project-URL: Bug Tracker, https://github.com/cristianpb/muse/issues
Project-URL: Changelog, https://github.com/cristianpb/muse/blob/master/README.md
Keywords: mopidy,muse,svelte
Classifier: Environment :: No Input/Output (Daemon)
Classifier: Intended Audience :: End Users/Desktop
Classifier: License :: OSI Approved :: Apache Software License
Classifier: Operating System :: OS Independent
Classifier: Programming Language :: Python :: 3
Classifier: Programming Language :: Python :: 3.9
Classifier: Programming Language :: Python :: 3.10
Classifier: Programming Language :: Python :: 3.11
Classifier: Topic :: Multimedia :: Sound/Audio :: Players
Requires-Python: >=3.8
License-File: LICENSE
Requires-Dist: Mopidy >=3.0.0
Requires-Dist: Pykka >=2.0.1
Requires-Dist: setuptools
Provides-Extra: pdf
Requires-Dist: ReportLab >=1.2 ; extra == 'pdf'
Requires-Dist: RXP ; extra == 'pdf'
Provides-Extra: rest
Requires-Dist: docutils >=0.3 ; extra == 'rest'
Requires-Dist: pack ==1.1,==1.3 ; extra == 'rest'
